codect/codect.py
codect-0.1.4.dist-info/METADATA
codect-0.1.4.dist-info/WHEEL
codect-0.1.4.dist-info/top_level.txt
codect-0.1.4.dist-info/RECORD
