Metadata-Version: 2.1
Name: codect
Version: 0.1.4
Summary: Python package to protect your code
Home-page: https://github.com/mategol/codect-python
Author: Mateusz Golembowski
Author-email: mateusz@golembowski.pl
License: MIT
Platform: UNKNOWN
Classifier: License :: OSI Approved :: MIT License
Classifier: Programming Language :: Python :: 3
Classifier: Operating System :: OS Independent
Requires-Dist: pycryptodome
Requires-Dist: pybase64
